taiga/__init__.py
taiga/client.py
taiga/exceptions.py
taiga/requestmaker.py
taiga/utils.py
taiga/models/__init__.py
taiga/models/base.py
taiga/models/models.py
python_taiga-1.3.2.dist-info/LICENSE
python_taiga-1.3.2.dist-info/METADATA
python_taiga-1.3.2.dist-info/WHEEL
python_taiga-1.3.2.dist-info/top_level.txt
python_taiga-1.3.2.dist-info/RECORD
