Metadata-Version: 2.2
Name: python-taiga
Version: 1.3.2
Summary: Taiga python API
Home-page: https://github.com/nephila/python-taiga
Author: Nephila
Author-email: team@team.nephila.digital
License: MIT
Keywords: taiga kanban wrapper api
Classifier: License :: OSI Approved :: MIT License
Classifier: Natural Language :: English
Classifier: Operating System :: OS Independent
Classifier: Development Status :: 5 - Production/Stable
Classifier: Programming Language :: Python
Classifier: Programming Language :: Python :: 3
Classifier: Programming Language :: Python :: 3.7
Classifier: Programming Language :: Python :: 3.8
Classifier: Programming Language :: Python :: 3.9
Classifier: Programming Language :: Python :: 3.10
Classifier: Programming Language :: Python :: 3.11
Requires-Python: >=3.7
License-File: LICENSE
Requires-Dist: requests>2.11
Requires-Dist: six>=1.9
Requires-Dist: python-dateutil>=2.4
Requires-Dist: pyjwkest>=1.0
Provides-Extra: docs
Requires-Dist: sphinx; extra == "docs"
Requires-Dist: sphinx-rtd-theme; extra == "docs"
